puzzle/__init__.py
puzzle/__main__.py
puzzle/_compat.py
puzzle/constants.py
puzzle/log.py
puzzle/cli/__init__.py
puzzle/cli/base.py
puzzle/cli/cases.py
puzzle/cli/delete.py
puzzle/cli/individuals.py
puzzle/cli/init.py
puzzle/cli/load.py
puzzle/cli/utils.py
puzzle/cli/view.py
puzzle/exceptions/__init__.py
puzzle/exceptions/database_exception.py
puzzle/models/__init__.py
puzzle/models/case.py
puzzle/models/compound.py
puzzle/models/dotdict.py
puzzle/models/gene.py
puzzle/models/genotype.py
puzzle/models/individual.py
puzzle/models/mixins.py
puzzle/models/transcript.py
puzzle/models/variant.py
puzzle/models/sql/__init__.py
puzzle/models/sql/genelist.py
puzzle/models/sql/models.py
puzzle/models/sql/phenotypeterm.py
puzzle/models/sql/query.py
puzzle/models/sql/resource.py
puzzle/plugins/__init__.py
puzzle/plugins/base.py
puzzle/plugins/base_case_mixin.py
puzzle/plugins/base_variant_mixin.py
puzzle/plugins/gemini/__init__.py
puzzle/plugins/gemini/case_mixin.py
puzzle/plugins/gemini/gemini_plugin.py
puzzle/plugins/gemini/variant_mixin.py
puzzle/plugins/sql/__init__.py
puzzle/plugins/sql/store.py
puzzle/plugins/vcf/__init__.py
puzzle/plugins/vcf/case_mixin.py
puzzle/plugins/vcf/variant_mixin.py
puzzle/plugins/vcf/vcf.py
puzzle/server/__init__.py
puzzle/server/ext.py
puzzle/server/factory.py
puzzle/server/settings.py
puzzle/server/blueprints/__init__.py
puzzle/server/blueprints/public/__init__.py
puzzle/server/blueprints/public/views.py
puzzle/server/blueprints/public/templates/case.html
puzzle/server/blueprints/public/templates/gene_list.html
puzzle/server/blueprints/public/templates/index.html
puzzle/server/blueprints/public/templates/individual.html
puzzle/server/blueprints/public/templates/individuals.html
puzzle/server/blueprints/public/templates/public_utils.html
puzzle/server/blueprints/public/templates/resource.html
puzzle/server/blueprints/variants/__init__.py
puzzle/server/blueprints/variants/views.py
puzzle-0.0.3.dist-info/DESCRIPTION.rst
puzzle-0.0.3.dist-info/METADATA
puzzle-0.0.3.dist-info/RECORD
puzzle-0.0.3.dist-info/WHEEL
puzzle-0.0.3.dist-info/entry_points.txt
puzzle-0.0.3.dist-info/metadata.json
puzzle-0.0.3.dist-info/top_level.txt
