Metadata-Version: 2.0
Name: puzzle
Version: 0.0.3
Summary: Web UI for searching genome variations
Home-page: https://github.com/robinandeer/puzzle
Author: Robin Andeer
Author-email: robin.andeer@gmail.com
License: MIT
Keywords: p,u,z,z,l,e, ,d,e,v,e,l,o,p,m,e,n,t
Platform: UNKNOWN
Classifier: Development Status :: 3 - Alpha
Classifier: Intended Audience :: Developers
Classifier: Topic :: Software Development
Classifier: License :: OSI Approved :: MIT License
Classifier: Programming Language :: Python :: 2
Classifier: Programming Language :: Python :: 2.7
Classifier: Programming Language :: Python :: 3
Classifier: Programming Language :: Python :: 3.3
Classifier: Programming Language :: Python :: 3.4
Classifier: Environment :: Console
Requires-Dist: Flask-Bootstrap
Requires-Dist: Flask-Script
Requires-Dist: click
Requires-Dist: intervaltree
Requires-Dist: path.py
Requires-Dist: ped-parser
Requires-Dist: phizz (>=0.1.1)
Requires-Dist: pyyaml
Requires-Dist: query-phenomizer (>=0.5)
Requires-Dist: setuptools
Requires-Dist: sqlalchemy
Requires-Dist: vcftoolbox (>=1.3.1)
